banidb/__init__.py
banidb/banidb.py
banidb/history.py
banidb-0.5.0.dist-info/LICENSE
banidb-0.5.0.dist-info/METADATA
banidb-0.5.0.dist-info/WHEEL
banidb-0.5.0.dist-info/top_level.txt
banidb-0.5.0.dist-info/RECORD
