Metadata-Version: 2.1
Name: banidb
Version: 0.5.0
Summary: Python Package for Sikh Gurbani - BaniDB API
Home-page: https://github.com/KhalisFoundation/banidb-api-python
Author: Khalis Foundation
Author-email: python@khalis.info
License: Open Software License 3.0 (OSL-3.0)
Download-URL: https://github.com/KhalisFoundation/banidb-api-python/archive/refs/tags/v_0.2.tar.gz
Project-URL: Source, https://github.com/KhalisFoundation/banidb-api-python
Project-URL: Issues, https://git.io/JG4II
Project-URL: Documentation, https://banidbpy.readthedocs.io/
Keywords: BaniDB,SikhiToTheMax,Gurbani,KhalisFoundation,Sikh,Guru Granth Sahib,API,Amrit Keertan,Sundar Gutka
Platform: UNKNOWN
Classifier: Development Status :: 4 - Beta
Classifier: Intended Audience :: Developers
Classifier: Intended Audience :: Religion
Classifier: Topic :: Software Development :: Libraries :: Python Modules
Classifier: License :: OSI Approved :: Open Software License 3.0 (OSL-3.0)
Classifier: Natural Language :: English
Classifier: Programming Language :: Python :: 3
Classifier: Programming Language :: Python :: 3.7
Classifier: Programming Language :: Python :: 3.8
Classifier: Programming Language :: Python :: 3.9
License-File: LICENSE
Requires-Dist: pep8-naming (==0.11.1)
Requires-Dist: pytest (==6.2.4)
Requires-Dist: flake8 (==3.9.2)
Requires-Dist: requests-mock (==1.9.3)
Requires-Dist: pytest-cov (==2.12.1)
Requires-Dist: bump2version (==1.0.1)
